meta2vec/.DS_Store
meta2vec/__init__.py
meta2vec/distance.py
meta2vec/utils.py
meta2vec/visualize.py
meta2vec-0.1.0.2.dist-info/METADATA
meta2vec-0.1.0.2.dist-info/WHEEL
meta2vec-0.1.0.2.dist-info/top_level.txt
meta2vec-0.1.0.2.dist-info/RECORD
