Metadata-Version: 2.1
Name: meta2vec
Version: 0.1.0.2
Summary: meta2vec, an embedding for Metabolomics study
Home-page: https://github.com/YuxingLu613/meta2vec
Author: Yuxing Lu
Author-email: yxlu0613@gmail.com
Classifier: Development Status :: 3 - Alpha
Classifier: License :: OSI Approved :: MIT License
Classifier: Programming Language :: Python :: 3
Classifier: Programming Language :: Python :: 3.6
Classifier: Programming Language :: Python :: 3.7
Classifier: Programming Language :: Python :: 3.8
Classifier: Programming Language :: Python :: 3
Classifier: License :: OSI Approved :: MIT License
Classifier: Operating System :: OS Independent
